nonebot_plugin_githubmodels/__init__.py
nonebot_plugin_githubmodels/config.py
nonebot_plugin_githubmodels/context_manager.py
nonebot_plugin_githubmodels/css/dark.css
nonebot_plugin_githubmodels/css/light.css
nonebot_plugin_githubmodels/openai_handler.py
nonebot_plugin_githubmodels-1.0.1.dist-info/WHEEL
nonebot_plugin_githubmodels-1.0.1.dist-info/METADATA
nonebot_plugin_githubmodels-1.0.1.dist-info/RECORD
