Metadata-Version: 2.4
Name: nonebot-plugin-githubmodels
Version: 1.0.1
Summary: NoneBot 集成 GitHub Copilot 和 OpenAI 的 AI 代码生成模型插件
Author: lyqgzbl
Author-email: lyqgzbl <122811297+lyqgzbl@users.noreply.github.com>
License-Expression: MIT
Requires-Dist: nonebot2>=2.2.1,<3.0.0
Requires-Dist: azure-ai-inference>=1.0.0b1,<2.0.0
Requires-Dist: nonebot-plugin-htmlrender>=0.5.0,<1.0.0
Requires-Dist: nonebot-plugin-alconna>=0.54.0,<1.0.0
Requires-Python: >=3.10, <4.0
Project-URL: documentation, https://github.com/lyqgzbl/nonebot-plugin-githubmodels#readme
Project-URL: homepage, https://github.com/lyqgzbl/nonebot-plugin-githubmodels
Project-URL: repository, https://github.com/lyqgzbl/nonebot-plugin-githubmodels
